django_api_decorator/__init__.py
django_api_decorator/apps.py
django_api_decorator/decorators.py
django_api_decorator/management/__init__.py
django_api_decorator/management/commands/__init__.py
django_api_decorator/management/commands/generate_api_schemas.py
django_api_decorator/openapi.py
django_api_decorator/py.typed
django_api_decorator/schema_file.py
django_api_decorator/types.py
django_api_decorator/utils.py
django_api_decorator-0.9.0.dist-info/LICENSE
django_api_decorator-0.9.0.dist-info/METADATA
django_api_decorator-0.9.0.dist-info/WHEEL
django_api_decorator-0.9.0.dist-info/RECORD
