Metadata-Version: 2.3
Name: django-api-decorator
Version: 0.9.0
Summary: A collection of tools to build function based Django APIs
License: MIT
Author: Oda
Author-email: tech@oda.com
Requires-Python: >=3.11,<4.0
Classifier: License :: OSI Approved :: MIT License
Classifier: Programming Language :: Python :: 3
Classifier: Programming Language :: Python :: 3.11
Classifier: Programming Language :: Python :: 3.12
Classifier: Programming Language :: Python :: 3.13
Requires-Dist: Django (>=4.2.16)
Requires-Dist: pydantic (>=2.0,<3.0)
Project-URL: Homepage, https://github.com/kolonialno/django-api-decorator
Project-URL: Repository, https://github.com/kolonialno/django-api-decorator
